file_path_parser/__init__.py
file_path_parser/api.py
file_path_parser/cli.py
file_path_parser/file_path_parser.py
file_path_parser/pattern_matcher.py
file_path_parser-0.1.5.dist-info/entry_points.txt
file_path_parser-0.1.5.dist-info/LICENSE
file_path_parser-0.1.5.dist-info/METADATA
file_path_parser-0.1.5.dist-info/WHEEL
file_path_parser-0.1.5.dist-info/RECORD
