Metadata-Version: 2.3
Name: file-path-parser
Version: 0.1.5
Summary: Universal, extensible Python library for extracting structured information (groups, dates, times, custom patterns) from file names and paths.
License: MIT
Keywords: filename,parser,path,date,time,regex,extract,pattern
Author: migutin83
Author-email: migutin83@yandex.ru
Requires-Python: >=3.8,<4.0
Classifier: Programming Language :: Python :: 3
Classifier: License :: OSI Approved :: MIT License
Classifier: Operating System :: OS Independent
Classifier: Intended Audience :: Developers
Classifier: Topic :: Software Development :: Libraries :: Python Modules
Classifier: Topic :: Utilities
Project-URL: Homepage, https://github.com/omigutin/file_path_parser
Project-URL: Issues, https://github.com/omigutin/file_path_parser/issues
